find_buildout_root.py
searchie_tools_find_buildout_root-0.0.2.dist-info/DESCRIPTION.rst
searchie_tools_find_buildout_root-0.0.2.dist-info/METADATA
searchie_tools_find_buildout_root-0.0.2.dist-info/RECORD
searchie_tools_find_buildout_root-0.0.2.dist-info/WHEEL
searchie_tools_find_buildout_root-0.0.2.dist-info/entry_points.txt
searchie_tools_find_buildout_root-0.0.2.dist-info/metadata.json
searchie_tools_find_buildout_root-0.0.2.dist-info/top_level.txt
